{
  "template": {
    "location": "https://github.com/cjolowicz/cookiecutter-hypermodern-python",
    "revision": "835de20c62fe142312783a18dc7d9b96e7587370",
    "directory": null
  },
  "bindings": {
    "project_name": "cookiecutter-hypermodern-python-instance",
    "package_name": "cookiecutter_hypermodern_python_instance",
    "friendly_name": "Cookiecutter Hypermodern Python Instance",
    "author": "Claudio Jolowicz",
    "email": "mail@claudiojolowicz.com",
    "github_user": "cjolowicz",
    "version": "0.0.0",
    "license": "MIT",
    "development_status": "Development Status :: 1 - Planning",
    "copyright_year": "2022"
  }
}
